portalocker/__about__.py
portalocker/__init__.py
portalocker/__main__.py
portalocker/constants.py
portalocker/exceptions.py
portalocker/portalocker.py
portalocker/py.typed
portalocker/redis.py
portalocker/types.py
portalocker/utils.py
portalocker-3.0.0.dist-info/LICENSE
portalocker-3.0.0.dist-info/METADATA
portalocker-3.0.0.dist-info/WHEEL
portalocker-3.0.0.dist-info/top_level.txt
portalocker-3.0.0.dist-info/RECORD
